JMS/__init__.py
JMS/JMS.py
robotframework_jmslibrary-0.3.0.dist-info/LICENSE
robotframework_jmslibrary-0.3.0.dist-info/METADATA
robotframework_jmslibrary-0.3.0.dist-info/WHEEL
robotframework_jmslibrary-0.3.0.dist-info/RECORD
