Metadata-Version: 2.1
Name: robotframework-jmslibrary
Version: 0.3.0
Summary: 
Author: Many Kasiriha
Author-email: many.kasiriha@dbschenker.com
Requires-Python: >=3.8.1,<4.0
Classifier: Programming Language :: Python :: 3
Classifier: Programming Language :: Python :: 3.9
Classifier: Programming Language :: Python :: 3.10
Classifier: Programming Language :: Python :: 3.11
Classifier: Programming Language :: Python :: 3.12
Classifier: Programming Language :: Python :: 3.13
Requires-Dist: jpype1
Requires-Dist: robotframework
Requires-Dist: robotframework-assertion-engine
